{
 "Week": "2025-05-14",
 "LastWeek": "",
 "X": 0.6856984123370227,
 "Programs": [
  {
   "Program": "cmd/asm",
   "Version": "go1.24.2",
   "GoVersion": "go1.24.2",
   "GOOS": "linux",
   "GOARCH": "amd64",
   "Counters": {
    "asm/flag:D": 48,
    "asm/flag:I": 48,
    "asm/flag:gensymabis": 14,
    "asm/flag:o": 48,
    "asm/flag:p": 48,
    "asm/flag:trimpath": 48,
    "asm/invocations": 48
   },
   "Stacks": {}
  },
  {
   "Program": "cmd/compile",
   "Version": "go1.24.2",
   "GoVersion": "go1.24.2",
   "GOOS": "linux",
   "GOARCH": "amd64",
   "Counters": {
    "compile/flag:asmhdr": 14,
    "compile/flag:buildid": 116,
    "compile/flag:c": 116,
    "compile/flag:complete": 97,
    "compile/flag:goversion": 116,
    "compile/flag:importcfg": 116,
    "compile/flag:lang": 116,
    "compile/flag:nolocalimports": 116,
    "compile/flag:o": 116,
    "compile/flag:p": 116,
    "compile/flag:pack": 116,
    "compile/flag:std": 96,
    "compile/flag:symabis": 14,
    "compile/flag:trimpath": 116,
    "compile/invocations": 128
   },
   "Stacks": {}
  },
  {
   "Program": "cmd/go",
   "Version": "go1.24.2",
   "GoVersion": "go1.24.2",
   "GOOS": "linux",
   "GOARCH": "amd64",
   "Counters": {
    "go/buildcache/miss": 117,
    "go/buildcache/stdlib-recompiled": 1,
    "go/goroot:usr-lib-go": 1,
    "go/install/flag:v": 1,
    "go/invocations": 1,
    "go/mode:module": 1,
    "go/platform/host/linux/major-version:6": 1,
    "go/platform/host/linux/version:6-14": 1,
    "go/platform/target/goamd64:v1": 1,
    "go/platform/target/goarch:amd64": 1,
    "go/platform/target/goos:linux": 1,
    "go/subcommand:install": 1
   },
   "Stacks": {}
  },
  {
   "Program": "cmd/link",
   "Version": "go1.24.2",
   "GoVersion": "go1.24.2",
   "GOOS": "linux",
   "GOARCH": "amd64",
   "Counters": {
    "link/flag:X": 1,
    "link/flag:buildid": 1,
    "link/flag:buildmode": 1,
    "link/flag:extld": 1,
    "link/flag:importcfg": 1,
    "link/flag:o": 1,
    "link/invocations": 2
   },
   "Stacks": {}
  }
 ],
 "Config": "v0.0.0-0"
}